CHANGES.rst
MANIFEST.in
README.rst
bootstrap.py
buildout.cfg
setup.py
src/zopache/__init__.py
src/zopache.pagetemplate.egg-info/PKG-INFO
src/zopache.pagetemplate.egg-info/SOURCES.txt
src/zopache.pagetemplate.egg-info/dependency_links.txt
src/zopache.pagetemplate.egg-info/namespace_packages.txt
src/zopache.pagetemplate.egg-info/not-zip-safe
src/zopache.pagetemplate.egg-info/requires.txt
src/zopache.pagetemplate.egg-info/top_level.txt
src/zopache/pagetemplate/__init__.py
src/zopache/pagetemplate/configure.zcml
src/zopache/pagetemplate/interfaces.py
src/zopache/pagetemplate/pagetemplate.py
src/zopache/pagetemplate/browser/__init__.py
src/zopache/pagetemplate/browser/configure.zcml
src/zopache/pagetemplate/browser/inlinecode.pt
src/zopache/pagetemplate/browser/pagetemplate.py
src/zopache/pagetemplate/browser/preview.pt
src/zopache/pagetemplate/browser/zpt.gif
src/zopache/pagetemplate/tests/__init__.py
src/zopache/pagetemplate/tests/test_pt.py
src/zopache/pagetemplate/tests/test_pteval.py